programmershousewrapper/__init__.py
programmershousewrapper/main.py
programmershousewrapper-2.2.9.dist-info/LICENSE
programmershousewrapper-2.2.9.dist-info/METADATA
programmershousewrapper-2.2.9.dist-info/WHEEL
programmershousewrapper-2.2.9.dist-info/top_level.txt
programmershousewrapper-2.2.9.dist-info/RECORD
