Metadata-Version: 2.1
Name: programmershousewrapper
Version: 2.2.9
Summary: ProgrammersHouse Api official wrapper
Home-page: https://www.programmershouse-api.ga
Author: Programmershouse
Author-email: houseprogrammers@gmail.com
License: UNKNOWN
Keywords: discord,discordpy,programmershouse,alets_ua
Platform: UNKNOWN
Classifier: Programming Language :: Python :: 3
Classifier: License :: OSI Approved :: MIT License
Classifier: Operating System :: OS Independent
Requires-Python: >=3.6
License-File: LICENSE
Requires-Dist: requests
